faramesh/__init__.py
faramesh/cli.py
faramesh/cli_actions.py
faramesh/cli_apply.py
faramesh/cli_shell.py
faramesh/cli_token.py
faramesh/integrations/__init__.py
faramesh/integrations/_client.py
faramesh/integrations/langchain/__init__.py
faramesh/integrations/langchain/governed_tool.py
faramesh/server/__init__.py
faramesh/server/auth.py
faramesh/server/canonicalization.py
faramesh/server/decision_engine.py
faramesh/server/errors.py
faramesh/server/events.py
faramesh/server/executor.py
faramesh/server/main.py
faramesh/server/metrics.py
faramesh/server/models.py
faramesh/server/policy_engine.py
faramesh/server/profiles.py
faramesh/server/settings.py
faramesh/server/storage.py
faramesh/server/storage_postgres.py
faramesh/server/security/__init__.py
faramesh/server/security/guard.py
faramesh-0.3.0.dist-info/licenses/LICENSE
faramesh-0.3.0.dist-info/licenses/NOTICE
faramesh-0.3.0.dist-info/METADATA
faramesh-0.3.0.dist-info/WHEEL
faramesh-0.3.0.dist-info/entry_points.txt
faramesh-0.3.0.dist-info/top_level.txt
faramesh-0.3.0.dist-info/RECORD
