Metadata-Version: 2.4
Name: faramesh
Version: 0.3.0
Summary: Faramesh — Minimal open-core agent action governor
Author: Faramesh Contributors
License: Elastic License 2.0
Requires-Python: >=3.9
License-File: LICENSE
License-File: NOTICE
Requires-Dist: fastapi>=0.103
Requires-Dist: uvicorn[standard]>=0.23
Requires-Dist: pydantic>=2.0
Requires-Dist: pydantic-settings>=2.0
Requires-Dist: pyyaml>=6.0
Requires-Dist: requests>=2.31
Requires-Dist: psycopg2-binary>=2.9
Requires-Dist: alembic>=1.13
Requires-Dist: prometheus-client>=0.19
Provides-Extra: test
Requires-Dist: pytest>=7.4; extra == "test"
Requires-Dist: pytest-asyncio>=0.21; extra == "test"
Requires-Dist: pytest-cov>=4.1; extra == "test"
Requires-Dist: httpx>=0.25; extra == "test"
Provides-Extra: dev
Requires-Dist: ruff>=0.3; extra == "dev"
Requires-Dist: flake8>=6.0; extra == "dev"
Requires-Dist: mypy>=1.0; extra == "dev"
Requires-Dist: types-requests; extra == "dev"
Provides-Extra: cli
Requires-Dist: rich>=13.0; extra == "cli"
Requires-Dist: tabulate>=0.9.0; extra == "cli"
Requires-Dist: watchdog>=3.0; extra == "cli"
Requires-Dist: sseclient>=0.0.27; extra == "cli"
Dynamic: license-file
